PyWebAutomator/WebAutomator.py
PyWebAutomator/__init__.py
PyWebAutomator-1.0.dist-info/LICENSE
PyWebAutomator-1.0.dist-info/METADATA
PyWebAutomator-1.0.dist-info/WHEEL
PyWebAutomator-1.0.dist-info/top_level.txt
PyWebAutomator-1.0.dist-info/RECORD
